powerdominationtoolbox/__init__.py
powerdominationtoolbox/powerdominationtoolbox.py
powerdominationtoolbox-2.6.dist-info/METADATA
powerdominationtoolbox-2.6.dist-info/WHEEL
powerdominationtoolbox-2.6.dist-info/licenses/LICENSE
powerdominationtoolbox-2.6.dist-info/RECORD
